<?xml version="1.0" encoding="utf-8"?>
<odoo>

    <record id="view_account_journal_digifact_form" model="ir.ui.view">
        <field name="name">account.journal.digifact.form</field>
        <field name="model">account.journal</field>
        <field name="inherit_id" ref="account.view_account_journal_form"/>
        <field name="arch" type="xml">
            <field name="code" position="before">
                <field name="is_fel"/>
                <field name="factura_cambiaria"/>
                <field name="is_nota_abono"/>
                <field name="codigo_est"/>
                <field name="no_cliente"/>
                <field name="usuario_ecofactura"/>
                <field name="password_ecofactura"/>
                <field name="nit_emisor"/>
                <field name="url_webservice"/>
                <field name="url_webservice_anulacion"/>
            </field>
        </field>
    </record>
</odoo>